appsurifyci/GitToAppsurify.py
appsurifyci/GitToAppsurifyDev.py
appsurifyci/RunTestsWithAppsurify3.py
appsurifyci/RunTestsWithAppsurify3_origin.py
appsurifyci/RunTestsWithAppsurifyDev.py
appsurifyci/TestImport.py
appsurifyci/__init__.py
appsurifyci/filenames.py
appsurifyci/testpython.py
appsurifyci/trxcpnvert.py
appsurifyci-0.1.30.dist-info/LICENCE.txt
appsurifyci-0.1.30.dist-info/METADATA
appsurifyci-0.1.30.dist-info/WHEEL
appsurifyci-0.1.30.dist-info/entry_points.txt
appsurifyci-0.1.30.dist-info/top_level.txt
appsurifyci-0.1.30.dist-info/RECORD
