Metadata-Version: 2.1
Name: appsurifyci
Version: 0.1.30
Summary: Package used to run tests using Appsurify
Home-page: https://appsurify.com
Author: James Farrier
Author-email: jamesfarrier@appsurify.com
License: MIT
Keywords: appsurify
Classifier: Development Status :: 5 - Production/Stable
Classifier: Intended Audience :: Education
Classifier: Operating System :: Microsoft :: Windows :: Windows 10
Classifier: License :: OSI Approved :: MIT License
Classifier: Programming Language :: Python :: 3
License-File: LICENCE.txt
Requires-Dist: PyYAML
Requires-Dist: requests
Requires-Dist: junitparser
Requires-Dist: appsurify-testbrain-contrib
